README.md
setup.cfg
setup.py
nanoevent/__init__.py
nanoevent/dispatcher.py
nanoevent.egg-info/PKG-INFO
nanoevent.egg-info/SOURCES.txt
nanoevent.egg-info/dependency_links.txt
nanoevent.egg-info/requires.txt
nanoevent.egg-info/top_level.txt