Metadata-Version: 2.1
Name: nanoevent
Version: 1.1.0
Summary: Nanoevent is a terrifically small and simple event bus implementation
Home-page: https://github.com/berry-langerak/nanoevent
Author: Berry Langerak
Author-email: berry.langerak@gmail.com
License: UNKNOWN
Platform: UNKNOWN
Classifier: Programming Language :: Python :: 3
Classifier: License :: OSI Approved :: MIT License
Classifier: Operating System :: OS Independent
Classifier: Development Status :: 5 - Production/Stable
Classifier: Intended Audience :: Developers
Requires-Python: >=3.6
Provides-Extra: test
